spongebobcase/VERSION
spongebobcase/__init__.py
spongebobcase/spongebobsay.py
spongebobcase/tospongebob.py
spongebobcase-0.4.1.dist-info/LICENSE
spongebobcase-0.4.1.dist-info/METADATA
spongebobcase-0.4.1.dist-info/WHEEL
spongebobcase-0.4.1.dist-info/top_level.txt
spongebobcase-0.4.1.dist-info/RECORD
