Metadata-Version: 2.1
Name: spongebobcase
Version: 0.4.1
Summary: SPoNgeBOb-CAse cONveRSioN iN PyTHoN.
Home-page: https://github.com/jayqi/spongebob
Author: Jay Qi
Author-email: jayqi.opensource@gmail.com
License: UNKNOWN
Keywords: mocking spongebob case,spongebob,spongebob case,spongebobsay
Platform: UNKNOWN
Classifier: Programming Language :: Python :: 3
Classifier: License :: OSI Approved :: BSD License
Classifier: Operating System :: OS Independent
Classifier: Topic :: Text Processing
Classifier: Topic :: Utilities
Requires-Python: >=3.6
